django_admin_otp-0.1.16.dist-info/METADATA
django_admin_otp-0.1.16.dist-info/WHEEL
django_admin_otp-0.1.16.dist-info/entry_points.txt
django_admin_otp/__init__.py
django_admin_otp/admin.py
django_admin_otp/apps.py
django_admin_otp/context_processors/__init__.py
django_admin_otp/context_processors/admin_otp.py
django_admin_otp/forms.py
django_admin_otp/middleware.py
django_admin_otp/migrations/0001_initial.py
django_admin_otp/migrations/__init__.py
django_admin_otp/models.py
django_admin_otp/settings.py
django_admin_otp/templates/admin/mfa_popup.html
django_admin_otp/templates/admin/otpverification_changelist.html
django_admin_otp/templates/mfa_setup.html
django_admin_otp/templates/mfa_verify.html
django_admin_otp/tests.py
django_admin_otp/urls.py
django_admin_otp/utils.py
django_admin_otp/views.py
django_admin_otp-0.1.16.dist-info/RECORD
