Metadata-Version: 2.1
Name: django-admin-otp
Version: 0.1.16
Summary: Implements Django Admin OTP Auth
Author-Email: whatislove118 <pochikalin@gmail.com>
License: MIT
Project-URL: Homepage, https://github.com/Whatislove118/django-admin-otp
Project-URL: Documentation, https://github.com/Whatislove118/django-admin-otp#readme
Requires-Python: <=3.13,>=3.10
Requires-Dist: qrcode>=8.2
Requires-Dist: pillow>=11.3.0
Requires-Dist: pyotp>=2.9.0
Provides-Extra: dev
Requires-Dist: django>=5.2.5; extra == "dev"
Requires-Dist: pre-commit>=4.3.0; extra == "dev"
Requires-Dist: ruff>=0.12.10; extra == "dev"
Requires-Dist: commitizen>=4.8.3; extra == "dev"
